pickle_scanner/__init__.py
pickle_scanner/__main__.py
pickle_scanner/cli.py
pickle_scanner/py.typed
pickle_scanner/analysis/__init__.py
pickle_scanner/analysis/ml_patterns.py
pickle_scanner/analysis/obfuscation.py
pickle_scanner/analysis/threat_intel.py
pickle_scanner/core/__init__.py
pickle_scanner/core/opcodes.py
pickle_scanner/core/scanner.py
pickle_scanner/core/stack_machine.py
pickle_scanner/formats/__init__.py
pickle_scanner/formats/detector.py
pickle_scanner/formats/pickle_parser.py
pickle_scanner/formats/torch_parser.py
pickle_scanner/reporting/__init__.py
pickle_scanner/reporting/json_output.py
pickle_scanner/reporting/report.py
pickle_scanner/rules/__init__.py
pickle_scanner/rules/builtin.py
pickle_scanner/rules/engine.py
pickleguard-1.0.0.dist-info/LICENSE
pickleguard-1.0.0.dist-info/METADATA
pickleguard-1.0.0.dist-info/WHEEL
pickleguard-1.0.0.dist-info/entry_points.txt
pickleguard-1.0.0.dist-info/top_level.txt
pickleguard-1.0.0.dist-info/RECORD
