Metadata-Version: 2.1
Name: pickleguard
Version: 1.0.0
Summary: Production-grade static analysis tool for detecting malicious Python pickle files
Author: PickleGuard Team
License: MIT
Project-URL: Homepage, https://github.com/yourusername/pickleguard
Project-URL: Documentation, https://github.com/yourusername/pickleguard#readme
Project-URL: Repository, https://github.com/yourusername/pickleguard.git
Project-URL: Issues, https://github.com/yourusername/pickleguard/issues
Project-URL: Changelog, https://github.com/yourusername/pickleguard/blob/main/CHANGELOG.md
Keywords: security,pickle,malware,static-analysis,machine-learning,pytorch,safetensors,vulnerability,scanner,ml-security,model-security
Classifier: Development Status :: 5 - Production/Stable
Classifier: Environment :: Console
Classifier: Intended Audience :: Developers
Classifier: Intended Audience :: Science/Research
Classifier: Intended Audience :: System Administrators
Classifier: License :: OSI Approved :: MIT License
Classifier: Operating System :: OS Independent
Classifier: Programming Language :: Python :: 3
Classifier: Programming Language :: Python :: 3.8
Classifier: Programming Language :: Python :: 3.9
Classifier: Programming Language :: Python :: 3.10
Classifier: Programming Language :: Python :: 3.11
Classifier: Programming Language :: Python :: 3.12
Classifier: Programming Language :: Python :: 3.13
Classifier: Topic :: Security
Classifier: Topic :: Scientific/Engineering :: Artificial Intelligence
Classifier: Topic :: Software Development :: Quality Assurance
Classifier: Typing :: Typed
Requires-Python: >=3.8
License-File: LICENSE
Requires-Dist: pyyaml>=5.0
Provides-Extra: dev
Requires-Dist: pytest>=7.0; extra == "dev"
Requires-Dist: pytest-cov>=4.0; extra == "dev"
Requires-Dist: black>=23.0; extra == "dev"
Requires-Dist: mypy>=1.0; extra == "dev"
Requires-Dist: ruff>=0.1.0; extra == "dev"
